baseImgX/__init__.py
baseImgX/baseImgX.py
baseToImgX-1.0.dist-info/LICENSE.txt
baseToImgX-1.0.dist-info/METADATA
baseToImgX-1.0.dist-info/WHEEL
baseToImgX-1.0.dist-info/top_level.txt
baseToImgX-1.0.dist-info/RECORD
