Metadata-Version: 2.1
Name: baseToImgX
Version: 1.0
Summary: 略略略
Author: xinian_night
Author-email: 1912681536@qq.com
Classifier: Programming Language :: Python :: 3
Classifier: License :: OSI Approved :: MIT License
Classifier: Operating System :: OS Independent
Requires-Python: >=3
License-File: LICENSE.txt
